{"fluctuate": ["[\u02c8fl\u028ckt\u0283\u028ae\u026at]", "v.", "\u6ce2\u52a8\uff0c\u53d8\u52a8\uff0c\u6da8\u843d"], "slot": ["[sl\u0252t]", "n.", "1.", "(\u53ef\u6295\u5165\u4e1c\u897f\u7684)\u5b54", "2.", "\u6c9f\uff0c\u69fd\uff0c\u6ed1\u9053", "3.", "\u5728\u540d\u5355\u3001\u7cfb\u7edf\u3001\u7ec4\u7ec7\u7b49\u4e2d\u7684\u4f4d\u7f6e\u3001\u7a7a\u4f4d", "v.", "1.", "\u5728(\u67d0\u7269)\u4e2d\u5f00\u7f3a\u53e3\u3001\u72ed\u7f1d\u3001\u6c9f\u69fd\u7b49", "2.", "\u628a\u2026\u5b89\u63d2\u5728\u7a7a\u4f4d\u4e2d\uff0c\u5b89\u7f6e"], "brutal": ["[\u02c8bru\u02d0t\u0259l]", "adj.", "\u6b8b\u5fcd\u7684\uff0c\u517d\u6027\u7684"], "minority": ["[ma\u026a\u02c8n\u0252r\u0259t\u026a]", "n.", "\u5c11\u6570\uff0c\u5c11\u6570\u6d3e\uff0c\u5c11\u6570\u6c11\u65cf"], "finite": ["[\u02c8fa\u026ana\u026at]", "adj.", "1.", "\u9650\u5b9a\u7684\uff0c\u6709\u9650\u7684", "2.", "(\u52a8\u8bcd)\u9650\u5b9a\u5f0f\u7684"], "device": ["[d\u026a\u02c8va\u026as]", "n.", "1.", "\u88c5\u7f6e\uff0c\u5668\u5177\uff0c\u4eea\u5668", "2.", "\u624b\u6bb5\uff0c\u7b56\u7565\uff0c\u8be1\u8ba1", "3.", "\u624b\u6cd5\uff0c\u6280\u5de7\uff0c\u56fe\u6848", "||", "leave", "to", "one\u2019s", "own", "devices\u542c\u4efb\u2026\u81ea\u4fbf\uff0c\u8ba9\u2026\u81ea\u884c\u53d1\u5c55"], "semester": ["[s\u026a\u02c8mest\u0259]", "n.", "\u4e00\u5b66\u671f"], "athlete": ["[\u02c8\u00e6\u03b8li\u02d0t]", "n.", "\u8fd0\u52a8\u5458"], "preach": ["[pri\u02d0t\u0283]", "v.", "1.", "\u8bb2\u9053\uff0c\u5e03\u9053", "2.", "\u8bf4\u6559\uff0c\u5ba3\u626c"], "redundant": ["[r\u026a\u02c8d\u028cnd\u0259nt]", "adj.", "1.", "(\u901a\u5e38\u6307\u8bed\u8a00\u6216\u827a\u672f)\u5197\u8d58\u7684\uff0c\u591a\u4f59\u7684", "2.", "(\u56e0\u4eba\u5458\u8fc7\u5269)\u88ab\u89e3\u96c7\u7684\uff0c\u5931\u4e1a\u7684"], "cradle": ["[\u02c8kre\u026adl]", "n.", "1.", "\u6447\u7bee", "", "2.", "\u7b56\u6e90\u5730\uff0c\u53d1\u6e90\u5730"], "mental": ["[\u02c8ment\u0259l]", "adj.", "1.", "\u5fc3\u667a\u7684\uff0c\u601d\u60f3\u7684", "2.", "\u7cbe\u795e\u75c5\u7684"], "scan": ["[sk\u00e6n]", "v.", "1.", "\u5ba1\u89c6\uff0c\u626b\u63cf", "2.", "\u6d4f\u89c8", "3.", "(\u6307\u8bd7\u53e5)\u7b26\u5408\u97f5\u5f8b", "n.", "\u5ba1\u89c6\uff0c\u626b\u63cf"], "embody": ["[\u026am\u02c8b\u0252d\u026a]", "v.", "\u4f53\u73b0\uff0c\u4f7f\u5177\u4f53\u5316"], "motive": ["[\u02c8m\u0259\u028at\u026av]", "n.", "\u52a8\u673a\uff0c\u76ee\u7684"]}