{"urban": ["[\u02c8\u025c\u02d0b\u0259n]", "adj.", "\u57ce\u5e02\u7684\uff0c\u90fd\u5e02\u7684"], "beforehand": ["[b\u026a\u02c8f\u0254\u02d0h\u00e6nd]", "adv.", "\u9884\u5148\uff0c\u4e8b\u5148"], "allege": ["[\u0259\u02c8led\u0292]", "v.", "(\u5728\u63d0\u4e0d\u51fa\u8bc1\u660e\u7684\u60c5\u51b5\u4e0b)\u65ad\u8a00\uff0c\u58f0\u79f0"], "comprehensive": ["[\u02cck\u0252mpr\u026a\u02c8hens\u026av]", "adj.", "1.", "\u7efc\u5408\u7684\uff0c\u5168\u9762\u7684", "2.", "\u7406\u89e3\u7684\uff0c\u6709\u7406\u89e3\u529b\u7684"], "intelligent": ["[\u026an\u02c8tel\u026ad\u0292\u0259nt]", "adj.", "\u806a\u660e\u7684\uff0c\u7406\u667a\u7684\uff0c\u660e\u667a\u7684"], "nasty": ["[\u02c8n\u0251\u02d0st\u026a]", "adj.", "1.", "\u4ee4\u4eba\u8ba8\u538c\u7684", "2.", "(\u6c14\u5473\u7b49)\u4ee4\u4eba\u4f5c\u5455\u7684", "3.", "\u5351\u9119\u7684", "nastily"], "rank": ["[r\u00e6\u014bk]", "n.", "1.", "\u6392\uff0c\u5217\uff0c\u884c", "", "2.", "\u519b\u8854\uff0c\u5730\u4f4d", "3.", "\u663e\u8d35\uff0c\u9ad8\u5730\u4f4d", "4.", "(pl)\u58eb\u5175", "5.", "\u961f\u5f62", "v.", "1.", "\u628a\u2026\u5206\u7b49\u7ea7\uff0c\u5217\u4e3a", "2.", "\u628a\u2026\u6392\u5217\u6574\u9f50"], "behavior": ["[bi\u02c8heivj\u04d9]", "n.", "\u884c\u4e3a\uff0c\u4e3e\u6b62"], "clip": ["2", "[kl\u026ap]", "n.", "\u5939\u5b50\uff0c\u7eb8\u5939"], "immune": ["[\u026a\u02c8mju\u02d0n]", "adj.", "\u6709\u514d\u75ab\u529b\u7684\uff0c\u4e0d\u53d7\u5f71\u54cd\u7684\uff0c\u83b7\u8c41\u514d\u7684", "", "immunity"], "spoil": ["[sp\u0254\u026al]", "v.", "1.", "\u635f\u574f\uff0c\u7cdf\u8e4b", "2.", "\u5ba0\u574f\uff0c\u6eba\u7231", "n.", "\u63a0\u593a\u7269\uff0c\u8d43\u7269"], "scatter": ["[\u02c8sk\u00e6t\u0259]", "v.", "1.", "\u4f7f\u5206\u6563\uff0c\u4f7f\u6d88\u6563", "2.", "\u6563\u64ad\uff0c\u6492\u64ad"], "interpret": ["[\u026an\u02c8t\u025c\u02d0pr\u026at]", "v.", "1.", "\u89e3\u91ca\uff0c\u8bf4\u660e", "2.", "\u4e86\u89e3\uff0c\u7406\u89e3\uff0c\u4f53\u73b0", "3.", "\u4f20\u8bd1\uff0c\u62c5\u4efb\u53e3\u8bd1"], "pact": ["[p\u00e6kt]", "n.", "\u5951\u7ea6\uff0c\u516c\u7ea6\uff0c\u6761\u7ea6"], "endeavor": ["[in\u02c8dev\u04d9]", "n.", "\u52aa\u529b\uff0c\u5c1d\u8bd5", "v.", "\u52aa\u529b\uff0c\u5c3d\u529b"]}