{"tuck": ["[t\u028ck]", "v.", "1.", "\u585e\u8fdb\uff0c\u63d2\u8fdb", "2.", "\u5377\u8d77\uff0c\u6298\u8d77", "3.", "\u6253\u8936\u6850"], "proof": ["2", "[pru\u02d0f]", "adj.", "\u9632\u2026\u7684\uff0c\u8010\u2026\u7684"], "unity": ["[\u02c8ju\u02d0n\u0259t\u026a]", "n.", "1.", "\u5355\u4e00\uff0cJ\u51c6\u4e00\uff0c\u7edf\u4e00\uff0c\u4e00\u4f53", "2.", "\u7edf\u4e00\u7684\u4e8b\u7269\uff0c\u7edf\u4e00\u4f53\uff0c\u6574\u4f53", "3.", "(\u76ee\u6807\u3001\u601d\u60f3\u3001\u60c5\u611f\u7b49)\u548c\u8c10\uff0c\u534f\u8c03\uff0c\u548c\u7766\uff0c\u56e2\u7ed3\uff0c\u4e00\u81f4"], "absence": ["[\u02c8\u00e6bs\u0259ns]", "n.", "1.", "\u7f3a\u5e2d", "2.", "\u7f3a\u4e4f\uff0c\u4e0d\u5b58\u5728"], "disgust": ["[d\u026as\u02c8\u0261\u028cst]", "n.", "\u538c\u6076\uff0c\u6076\u5fc3\uff0c\u4f5c\u5455", "v.", "\u4f7f\u8ba8\u538c\uff0c\u4f7f\u538c\u6076\uff0c\u4f7f\u4f5c\u5455"], "costume": ["[\u02c8k\u0252stju\u02d0m]", "n.", "\u670d\u88c5\uff0c\u5267\u88c5\uff0c\u620f\u670d"], "capable": ["[\u02c8ke\u026ap\u0259bl]", "adj.", "\u6709\u80fd\u529b\u7684\uff0c\u6709\u624d\u80fd\u7684"], "bound": ["3", "[ba\u028and]", "adj.", "\u5f00\u5f80\u2026\u7684"], "periodical": ["[\u02ccp\u026a\u0259r\u026a\u02c8\u0252d\u026ak\u0259l]", "adj.", "\u5b9a\u671f\u7684\uff0c\u5468\u671f\u7684", "n.", "\u671f\u520a\uff0c\u6742\u5fd7"], "assurance": ["[\u0259\u02c8\u0283\u028a\u0259r\u0259ns]", "n.", "1.", "\u62c5\u4fdd\uff0c\u4fdd\u8bc1", "2.", "\u80af\u5b9a\uff0c\u786e\u4fe1", "3.", "\u81ea\u4fe1"], "incur": ["[\u026an\u02c8k\u025c\u02d0]", "v.", "\u906d\u53d7\uff0c\u8499\u53d7\uff0c\u62db\u81f4"], "tunnel": ["[\u02c8t\u028cn\u0259l]", "n.", "\u96a7\u9053\uff0c\u5751\u9053", "v.", "\u5f00\u96a7\u9053\uff0c\u5f00\u96a7\u9053\u7a7f\u8fc7"], "blush": ["[bl\u028c\u0283]", "n.", "\u8138\u7ea2", "v.", "\u611f\u5230\u7f9e\u6127"], "lens": ["[lenz]", "n.", "1.", "\u900f\u955c", "2.", "(\u773c\u7403\u7684)\u6676\u72b6\u4f53", "3.", "\u9690\u5f62\u773c\u955c"], "probe": ["[pr\u0259\u028ab]", "n.", "1.", "\u63a2\u9488", "2", "\u63a2\u6d4b\u98de\u8239", "3.", "\u63a2\u67e5\uff0c\u5f7b\u5e95\u8c03\u67e5", "v.", "\u63a2\u67e5\uff0c\u67e5\u7a76"]}